mlserve_sdk/__init__.py
mlserve_sdk/client.py
mlserve_sdk/rl_plots.py
mlserve_sdk-0.4.0.dist-info/licenses/LICENSE.txt
mlserve_sdk-0.4.0.dist-info/METADATA
mlserve_sdk-0.4.0.dist-info/WHEEL
mlserve_sdk-0.4.0.dist-info/top_level.txt
mlserve_sdk-0.4.0.dist-info/RECORD
